yacmmal/__init__.py
yacmmal/base.py
yacmmal/load/__init__.py
yacmmal/load/base.py
yacmmal/load/yaml.py
yacmmal/types/__init__.py
yacmmal/types/config.py
yacmmal-0.1.0.dist-info/WHEEL
yacmmal-0.1.0.dist-info/METADATA
yacmmal-0.1.0.dist-info/RECORD
